setup.py
PPyNet/__init__.py
PPyNet/connection.py
PPyNet/p2p.py
PPyNet/rawws.py
ppynet.egg-info/PKG-INFO
ppynet.egg-info/SOURCES.txt
ppynet.egg-info/dependency_links.txt
ppynet.egg-info/requires.txt
ppynet.egg-info/top_level.txt