Metadata-Version: 2.1
Name: ppynet
Version: 0.0.4
Summary: An easy to use low level websocket based utility package.
Home-page: UNKNOWN
Author: Darkodaaa
Author-email: 
License: UNKNOWN
Keywords: python,sockets,connection,utility
Platform: UNKNOWN
Classifier: Development Status :: 3 - Alpha
Classifier: Intended Audience :: Developers
Classifier: Programming Language :: Python :: 3
Classifier: Operating System :: Unix
Classifier: Operating System :: MacOS :: MacOS X
Classifier: Operating System :: Microsoft :: Windows
